{
    "erc_file_006.doc": {
        "Родительская папка": "dir",
        "Тип объекта": "Файл",
        "Размер": 880
    },
    "gdj_file_004.doc": {
        "Родительская папка": "dir",
        "Тип объекта": "Файл",
        "Размер": 2541
    },
    "lnb_file_002.doc": {
        "Родительская папка": "dir",
        "Тип объекта": "Файл",
        "Размер": 4053
    },
    "nevernever.json": {
        "Родительская папка": "dir",
        "Тип объекта": "Файл",
        "Размер": 0
    },
    "pmn_file_001.doc": {
        "Родительская папка": "dir",
        "Тип объекта": "Файл",
        "Размер": 1438
    },
    "zjc_file_003.doc": {
        "Родительская папка": "dir",
        "Тип объекта": "Файл",
        "Размер": 3417
    },
    "zpz_file_005.doc": {
        "Родительская папка": "dir",
        "Тип объекта": "Файл",
        "Размер": 3663
    }
}